dagger.cpython-313-darwin.so
daggerpy-0.0.17.dist-info/METADATA
daggerpy-0.0.17.dist-info/WHEEL
daggerpy-0.0.17.dist-info/entry_points.txt
daggerpy-0.0.17.dist-info/top_level.txt
daggerpy-0.0.17.dist-info/RECORD
