Metadata-Version: 2.4
Name: daggerpy
Version: 0.0.17
Summary: DAG tools to process numerical topography and landscape evolution models
Home-page: https://github.com/bgailleton/DAGGER
Author: Boris Gailleton
Author-email: boris.gailleton@univ-rennes.fr
License: GNU General Public License v3
Keywords: dagger
Classifier: Development Status :: 2 - Pre-Alpha
Classifier: Intended Audience :: Developers
Classifier: License :: OSI Approved :: GNU General Public License v3 (GPLv3)
Classifier: Natural Language :: English
Classifier: Programming Language :: Python :: 3
Classifier: Programming Language :: Python :: 3.6
Classifier: Programming Language :: Python :: 3.7
Classifier: Programming Language :: Python :: 3.8
Classifier: Programming Language :: Python :: 3.9
Classifier: Programming Language :: Python :: 3.10
Classifier: Programming Language :: Python :: 3.11
Requires-Python: >=3.6
Requires-Dist: Click>=7.0
Requires-Dist: pybind11
Requires-Dist: numpy>=2
Dynamic: author
Dynamic: author-email
Dynamic: classifier
Dynamic: description
Dynamic: home-page
Dynamic: keywords
Dynamic: license
Dynamic: requires-dist
Dynamic: requires-python
Dynamic: summary
